toolhouse/README.md
toolhouse/__init__.py
toolhouse/exceptions.py
toolhouse/py.typed
toolhouse/sdk.py
toolhouse/hooks/__init__.py
toolhouse/hooks/hook.py
toolhouse/models/AnthropicToolCall.py
toolhouse/models/AnthropicToolCallResults.py
toolhouse/models/AntropicTools.py
toolhouse/models/FunctionParameters.py
toolhouse/models/GenericArgument.py
toolhouse/models/GenericToolCall.py
toolhouse/models/GenericToolCallResults.py
toolhouse/models/GenericTools.py
toolhouse/models/GetToolsRequest.py
toolhouse/models/GetToolsResponse.py
toolhouse/models/OpenAiAssistantsFunction.py
toolhouse/models/OpenAiAssistantsToolCall.py
toolhouse/models/OpenAiFunction.py
toolhouse/models/OpenAiFunctionDefinition.py
toolhouse/models/OpenAiToolAssistantsCallResults.py
toolhouse/models/OpenAiToolCall.py
toolhouse/models/OpenAiToolCallResults.py
toolhouse/models/OpenAiTools.py
toolhouse/models/Provider.py
toolhouse/models/RunLocalTools.py
toolhouse/models/RunToolsRequest.py
toolhouse/models/Stream.py
toolhouse/models/ToolhouseCallResults.py
toolhouse/models/__init__.py
toolhouse/models/base.py
toolhouse/models/tools_models/__init__.py
toolhouse/models/tools_models/anthropic.py
toolhouse/models/tools_models/openai.py
toolhouse/models/tools_models/toolhouse.py
toolhouse/net/__init__.py
toolhouse/net/environment.py
toolhouse/net/http_client.py
toolhouse/net/http_content_types.py
toolhouse/net/query_serializer.py
toolhouse/net/utils.py
toolhouse/services/__init__.py
toolhouse/services/base.py
toolhouse/services/llamaindex.py
toolhouse/services/local_tools.py
toolhouse/services/tools.py
toolhouse-1.4.0.dist-info/METADATA
toolhouse-1.4.0.dist-info/WHEEL
toolhouse-1.4.0.dist-info/licenses/LICENSE
toolhouse-1.4.0.dist-info/RECORD
