Metadata-Version: 2.4
Name: toolhouse
Version: 1.4.0
Summary: The official Python SDK for the Toolhouse API
Project-URL: Homepage, https://toolhouse.ai
Project-URL: Repository, https://github.com/toolhouseai/toolhouse-sdk-python
Project-URL: Documentation, https://docs.toolhouse.ai
Project-URL: Bug Tracker, https://github.com/toolhouseai/toolhouse-sdk-python/issues
Project-URL: Release Notes, https://github.com/toolhouseai/toolhouse-sdk-python/releases
Author-email: Toolhouse Technologies <hello@toolhouse.ai>
Maintainer-email: Toolhouse Technologies <hello@toolhouse.ai>
License: 
License-File: LICENSE
Keywords: ai,llm,sdk,toolhouse
Classifier: Intended Audience :: Developers
Classifier: License :: OSI Approved :: Apache Software License
Classifier: Operating System :: MacOS
Classifier: Operating System :: Microsoft :: Windows
Classifier: Operating System :: OS Independent
Classifier: Operating System :: POSIX
Classifier: Operating System :: POSIX :: Linux
Classifier: Programming Language :: Python :: 3.9
Classifier: Programming Language :: Python :: 3.10
Classifier: Programming Language :: Python :: 3.11
Classifier: Programming Language :: Python :: 3.12
Classifier: Topic :: Software Development :: Libraries :: Python Modules
Classifier: Typing :: Typed
Requires-Python: <4.0,>=3.9
Requires-Dist: anthropic
Requires-Dist: groq
Requires-Dist: http-exceptions
Requires-Dist: openai
Requires-Dist: python-dotenv>=1.0.1
Requires-Dist: requests
Provides-Extra: llamaindex
Requires-Dist: llama-index<0.13.0,>=0.12.19; extra == 'llamaindex'
Provides-Extra: test
Requires-Dist: pytest; extra == 'test'
Requires-Dist: responses; extra == 'test'
